README.rst
setup.py
Flask_Venom.egg-info/PKG-INFO
Flask_Venom.egg-info/SOURCES.txt
Flask_Venom.egg-info/dependency_links.txt
Flask_Venom.egg-info/not-zip-safe
Flask_Venom.egg-info/requires.txt
Flask_Venom.egg-info/top_level.txt
flask_venom/__init__.py
flask_venom/test_utils.py
flask_venom/utils.py